ozqis/__init__.py
ozqis/calculate.py
ozqis/quantum_relative_entropy.py
ozqis-1.0.0.dist-info/LICENSE
ozqis-1.0.0.dist-info/METADATA
ozqis-1.0.0.dist-info/WHEEL
ozqis-1.0.0.dist-info/top_level.txt
ozqis-1.0.0.dist-info/RECORD
